feta/__init__.py
feta/__version__.py
feta/cli.py
feta-0.1.0.dist-info/LICENSE
feta-0.1.0.dist-info/METADATA
feta-0.1.0.dist-info/WHEEL
feta-0.1.0.dist-info/top_level.txt
feta-0.1.0.dist-info/RECORD
