Metadata-Version: 2.1
Name: feta
Version: 0.1.0
Summary: A cookiecutter for command-line tools!
Home-page: https://github.com/vinayak-mehta/feta
Author: Vinayak Mehta
Author-email: vmehta94@gmail.com
License: Apache 2.0
Platform: UNKNOWN
Classifier: License :: OSI Approved :: Apache Software License
Classifier: Programming Language :: Python :: 3.6
Classifier: Programming Language :: Python :: 3.7
Requires-Dist: Click (>=7.0)
Provides-Extra: dev
Requires-Dist: Sphinx (>=2.2.1) ; extra == 'dev'
Requires-Dist: Click (>=7.0) ; extra == 'dev'
